CHANGELOG.rst
LICENSE
MANIFEST.in
README.rst
setup.py
argonauts/__init__.py
argonauts/http.py
argonauts/models.py
argonauts/serializers.py
argonauts/testutils.py
argonauts/views.py
argonauts/templatetags/__init__.py
argonauts/templatetags/argonauts.py
django_argonauts.egg-info/PKG-INFO
django_argonauts.egg-info/SOURCES.txt
django_argonauts.egg-info/dependency_links.txt
django_argonauts.egg-info/requires.txt
django_argonauts.egg-info/top_level.txt