Metadata-Version: 1.1
Name: django-argonauts
Version: 1.1.4
Summary: A lightweight collection of JSON helpers for Django.
Home-page: https://github.com/fusionbox/django-argonauts
Author: Fusionbox, Inc.
Author-email: programmers@fusionbox.com
License: UNKNOWN
Keywords: rest json views django helpers
Platform: UNKNOWN
Classifier: Development Status :: 5 - Production/Stable
Classifier: Framework :: Django
Classifier: Intended Audience :: Developers
Classifier: License :: OSI Approved :: BSD License
Classifier: Topic :: Internet :: WWW/HTTP
Classifier: Topic :: Software Development :: Libraries
Classifier: Programming Language :: Python
Classifier: Programming Language :: Python :: 2.6
Classifier: Programming Language :: Python :: 2.7
Classifier: Programming Language :: Python :: 3.3
Classifier: Programming Language :: Python :: 3.4
